odoo/addons/repair_scheduled_date_calendar_view/README.rst
odoo/addons/repair_scheduled_date_calendar_view/__init__.py
odoo/addons/repair_scheduled_date_calendar_view/__manifest__.py
odoo/addons/repair_scheduled_date_calendar_view/i18n/it.po
odoo/addons/repair_scheduled_date_calendar_view/i18n/repair_scheduled_date_calendar_view.pot
odoo/addons/repair_scheduled_date_calendar_view/models/__init__.py
odoo/addons/repair_scheduled_date_calendar_view/models/repair_order.py
odoo/addons/repair_scheduled_date_calendar_view/models/res_config_settings.py
odoo/addons/repair_scheduled_date_calendar_view/readme/CONFIGURE.md
odoo/addons/repair_scheduled_date_calendar_view/readme/CONTEXT.md
odoo/addons/repair_scheduled_date_calendar_view/readme/CONTRIBUTORS.md
odoo/addons/repair_scheduled_date_calendar_view/readme/DESCRIPTION.md
odoo/addons/repair_scheduled_date_calendar_view/readme/USAGE.md
odoo/addons/repair_scheduled_date_calendar_view/readme/newsfragments/.gitkeep
odoo/addons/repair_scheduled_date_calendar_view/static/description/icon.png
odoo/addons/repair_scheduled_date_calendar_view/static/description/icon.svg
odoo/addons/repair_scheduled_date_calendar_view/static/description/index.html
odoo/addons/repair_scheduled_date_calendar_view/tests/__init__.py
odoo/addons/repair_scheduled_date_calendar_view/tests/test_repair_calendar.py
odoo/addons/repair_scheduled_date_calendar_view/views/repair_order_views.xml
odoo/addons/repair_scheduled_date_calendar_view/views/res_config_settings_views.xml
odoo/addons/repair_scheduled_date_calendar_view/views/view_repair_order_form.xml
odoo_addon_repair_scheduled_date_calendar_view-18.0.1.0.0.4.dist-info/METADATA
odoo_addon_repair_scheduled_date_calendar_view-18.0.1.0.0.4.dist-info/WHEEL
odoo_addon_repair_scheduled_date_calendar_view-18.0.1.0.0.4.dist-info/top_level.txt
odoo_addon_repair_scheduled_date_calendar_view-18.0.1.0.0.4.dist-info/RECORD
