Metadata-Version: 2.1
Name: odoo-addon-repair_scheduled_date_calendar_view
Version: 18.0.1.0.0.4
Requires-Python: >=3.10
Requires-Dist: odoo-addon-base_repair_config==18.0.*
Requires-Dist: odoo==18.0.*
Summary: Repair order calendar view based on scheduled data
Home-page: https://github.com/OCA/repair
License: AGPL-3
Author: Cetmix, Odoo Community Association (OCA)
Author-email: support@odoo-community.org
Classifier: Programming Language :: Python
Classifier: Framework :: Odoo
Classifier: Framework :: Odoo :: 18.0
Classifier: License :: OSI Approved :: GNU Affero General Public License v3
